pyspark_json_model/__init__.py
pyspark_json_model/jsontools.py
pyspark_json_model-0.0.3.dist-info/LICENSE.rst
pyspark_json_model-0.0.3.dist-info/METADATA
pyspark_json_model-0.0.3.dist-info/WHEEL
pyspark_json_model-0.0.3.dist-info/top_level.txt
pyspark_json_model-0.0.3.dist-info/RECORD
