Metadata-Version: 2.1
Name: pyspark-json-model
Version: 0.0.3
Summary: JSON to Relational data model through Pyspark using Databricks
Home-page: https://github.com/rohitpawar95/pyspark_json_model
Author: Rohit Pawar
Author-email: rohitpawar95@outlook.com
License: MIT
Download-URL: https://pypi.org/project/pyspark_json_model/
Keywords: Pyspark,Spark,JSON,Data Model,Python,JSON Flatten,Databricks
Platform: UNKNOWN
License-File: LICENSE.rst
